[
    {
        "model": "point_of_sales.documenttype",
        "pk": 1,
        "fields": {
            "name": "N/A",
            "status": true
        }
    },
    {
        "model": "point_of_sales.documenttype",
        "pk": 2,
        "fields": {
            "name": "CEDULA",
            "status": true
        }
    },
    {
        "model": "point_of_sales.documenttype",
        "pk": 3,
        "fields": {
            "name": "PASAPORTE",
            "status": true
        }
    },
    {
        "model": "point_of_sales.documenttype",
        "pk": 4,
        "fields": {
            "name": "RNC",
            "status": true
        }
    }
]